dockrich/__init__.py
dockrich/dockcompose.py
dockrich/dockerclimanager.py
dockrich/dockerhistory.py
dockrich/dockerinspector.py
dockrich/dockermanage.py
dockrich/dockerstats.py
dockrich/dockrich.py
dockrich-0.5.dist-info/LICENSE
dockrich-0.5.dist-info/METADATA
dockrich-0.5.dist-info/WHEEL
dockrich-0.5.dist-info/entry_points.txt
dockrich-0.5.dist-info/top_level.txt
dockrich-0.5.dist-info/RECORD
